dataset/djmix-dataset.json.gz
djmix/__init__.py
djmix/audio.py
djmix/bootstrap.py
djmix/config.py
djmix/download.py
djmix/models/Audio.py
djmix/models/Mix.py
djmix/models/Track.py
djmix/models/__init__.py
djmix/tools/__init__.py
djmix/tools/alignment/__init__.py
djmix/tools/alignment/dtw.py
djmix/tools/alignment/helpers.py
djmix/tools/alignment/transitions.py
djmix/tools/alignment/tsm.py
djmix/tools/cvxopt/__init__.py
djmix/tools/cvxopt/optimize.py
djmix/tools/cvxopt/optimizers/__init__.py
djmix/tools/cvxopt/optimizers/eq3_fader_optimizer.py
djmix/tools/cvxopt/optimizers/eq3_optimizer.py
djmix/tools/cvxopt/optimizers/fader_optimizer.py
djmix/tools/cvxopt/optimizers/optimizer.py
djmix/tools/eq/__init__.py
djmix/tools/eq/biquad_filters.py
djmix/tools/eq/eq3.py
djmix/tools/eq/reconstruct.py
djmix/tools/features/__init__.py
djmix/tools/features/beats.py
djmix/tools/features/cache.py
djmix/tools/features/spectrograms.py
djmix/utils.py
djmix-0.3.1.dist-info/WHEEL
djmix-0.3.1.dist-info/METADATA
djmix-0.3.1.dist-info/RECORD
