Metadata-Version: 2.1
Name: djmix
Version: 0.3.1
Summary: 
Author: Taejun Kim
Author-email: taejun@kaist.ac.kr
Requires-Python: >=3.7,<3.11
Classifier: Programming Language :: Python :: 3
Classifier: Programming Language :: Python :: 3.10
Classifier: Programming Language :: Python :: 3.7
Classifier: Programming Language :: Python :: 3.8
Classifier: Programming Language :: Python :: 3.9
Provides-Extra: tools
Requires-Dist: cvxpy (>=1.2.2,<2.0.0); extra == "tools"
Requires-Dist: joblib (>=1.2.0,<2.0.0); extra == "tools"
Requires-Dist: librosa (>=0.9.2,<0.10.0); extra == "tools"
Requires-Dist: madmom (>=0.16.1,<0.17.0); extra == "tools"
Requires-Dist: matplotlib (>=3.6.2,<4.0.0); extra == "tools"
Requires-Dist: pandas (>=1.5.2,<2.0.0); extra == "tools"
Requires-Dist: pydantic (>=1.10.2,<2.0.0)
Requires-Dist: pydub (>=0.25.1,<0.26.0); extra == "tools"
Requires-Dist: pytsmod (>=0.3.6,<0.4.0); extra == "tools"
Requires-Dist: scikit-image (>=0.19.3,<0.20.0); extra == "tools"
Requires-Dist: yt-dlp
